LICENSE
MANIFEST.in
README.rst
morton.py
setup.py
test.py
morton_py.egg-info/PKG-INFO
morton_py.egg-info/SOURCES.txt
morton_py.egg-info/dependency_links.txt
morton_py.egg-info/top_level.txt