Metadata-Version: 1.1
Name: morton-py
Version: 1.1
Summary: Morton code pack/unpack library
Home-page: https://github.com/gojuno/morton-py
Author: Alexander Verbitsky
Author-email: averbitsky@gojuno.com
License: BSD
Keywords: z-order,morton coding,hashing
Platform: UNKNOWN
Classifier: Development Status :: 5 - Production/Stable
Classifier: Topic :: Utilities
Classifier: Programming Language :: Python
Classifier: License :: OSI Approved :: BSD License
